python_bunny_mq/__init__.py
python_bunny_mq/bounded_dict.py
python_bunny_mq/bunny_mq.py
python_bunny_mq/test_bunny_queue.py
python_bunny_mq-0.1.8.dist-info/METADATA
python_bunny_mq-0.1.8.dist-info/WHEEL
python_bunny_mq-0.1.8.dist-info/RECORD
