Metadata-Version: 2.1
Name: python-bunny-mq
Version: 0.1.8
Summary: Ultra-lightweight (no-dependency) message queue for intra-process pub-sub communication.
Home-page: https://pypi.org/project/python-bunny-mq/
License: Unlicense
Author: Steven Miers
Author-email: steven.miers@gmail.com
Requires-Python: >=3.12,<4.0
Classifier: License :: OSI Approved
Classifier: Programming Language :: Python :: 3
Classifier: Programming Language :: Python :: 3.12
Project-URL: Documentation, https://tangledpath.github.io/python-bunny-mq
Project-URL: Repository, https://github.com/tangledpath/python-bunny-mq
